bdranalytics/__init__.py
bdranalytics/images/__init__.py
bdranalytics/images/bdr.gif
bdranalytics/keras/__init__.py
bdranalytics/keras/callbacks.py
bdranalytics/keras/generators.py
bdranalytics/keras/layers.py
bdranalytics/pdlearn/__init__.py
bdranalytics/pdlearn/pipeline.py
bdranalytics/pdlearn/preprocessing.py
bdranalytics/plot/__init__.py
bdranalytics/plot/classification.py
bdranalytics/sklearn/__init__.py
bdranalytics/sklearn/encoders.py
bdranalytics/sklearn/model_selection.py
bdranalytics-0.1.dist-info/DESCRIPTION.rst
bdranalytics-0.1.dist-info/METADATA
bdranalytics-0.1.dist-info/RECORD
bdranalytics-0.1.dist-info/WHEEL
bdranalytics-0.1.dist-info/metadata.json
bdranalytics-0.1.dist-info/top_level.txt
