Metadata-Version: 2.0
Name: bdranalytics
Version: 0.1
Summary: Our analytics library to quickly get our data scientists up to speed
Home-page: https://github.com/BigDataRepublic/bdr-analytics-py
Author: BigData Republic
Author-email: info@bigdatarepublic.nl
License: Apache License 2.0
Platform: UNKNOWN
Requires-Python: >=2.6, <3
Requires-Dist: NumPy (>=1.6.1)
Requires-Dist: SciPy (>=0.9)
Requires-Dist: scikit-learn (>=0.18)
Requires-Dist: pandas
Requires-Dist: seaborn
Requires-Dist: matplotlib
Requires-Dist: pandas-profiling
Requires-Dist: tensorboard
